lanplay/__init__.py
lanplay/lanplay.py
lanplaypy-1.0.0.dist-info/LICENCE
lanplaypy-1.0.0.dist-info/METADATA
lanplaypy-1.0.0.dist-info/WHEEL
lanplaypy-1.0.0.dist-info/top_level.txt
lanplaypy-1.0.0.dist-info/RECORD
