Metadata-Version: 2.1
Name: lanplaypy
Version: 1.0.0
Summary: LAN-PLAY API Python
Home-page: https://github.com/LeGeRyChEeSe/lanplaypy
Author: Kilian Douarinou
Author-email: kilian.douarinou41@gmail.com
License: MIT
Keywords: LAN-PLAY API Python GraphQL
Classifier: Development Status :: 5 - Production/Stable
Classifier: Intended Audience :: Developers
Classifier: Topic :: Software Development :: Libraries :: Python Modules
Classifier: License :: OSI Approved :: MIT License
Classifier: Programming Language :: Python :: 3.9
Requires-Python: >=3.9
License-File: LICENCE
Requires-Dist: gql[aiohttp]
Requires-Dist: requests
